wikiteam3/__init__.py
wikiteam3/dumpgenerator/__init__.py
wikiteam3/dumpgenerator/__main__.py
wikiteam3/dumpgenerator/api/__init__.py
wikiteam3/dumpgenerator/api/api.py
wikiteam3/dumpgenerator/api/get_json.py
wikiteam3/dumpgenerator/api/handle_status_code.py
wikiteam3/dumpgenerator/api/index_check.py
wikiteam3/dumpgenerator/api/namespaces.py
wikiteam3/dumpgenerator/api/page_titles.py
wikiteam3/dumpgenerator/api/wiki_check.py
wikiteam3/dumpgenerator/cli/__init__.py
wikiteam3/dumpgenerator/cli/cli.py
wikiteam3/dumpgenerator/cli/delay.py
wikiteam3/dumpgenerator/cli/greeter.py
wikiteam3/dumpgenerator/config.py
wikiteam3/dumpgenerator/dump/__init__.py
wikiteam3/dumpgenerator/dump/generator.py
wikiteam3/dumpgenerator/dump/image/__init__.py
wikiteam3/dumpgenerator/dump/image/html_regexs.py
wikiteam3/dumpgenerator/dump/image/image.py
wikiteam3/dumpgenerator/dump/misc/__init__.py
wikiteam3/dumpgenerator/dump/misc/index_php.py
wikiteam3/dumpgenerator/dump/misc/site_info.py
wikiteam3/dumpgenerator/dump/misc/special_logs.py
wikiteam3/dumpgenerator/dump/misc/special_version.py
wikiteam3/dumpgenerator/dump/page/__init__.py
wikiteam3/dumpgenerator/dump/page/xmlexport/__init__.py
wikiteam3/dumpgenerator/dump/page/xmlexport/page_xml.py
wikiteam3/dumpgenerator/dump/page/xmlexport/page_xml_api.py
wikiteam3/dumpgenerator/dump/page/xmlexport/page_xml_export.py
wikiteam3/dumpgenerator/dump/page/xmlrev/__init__.py
wikiteam3/dumpgenerator/dump/page/xmlrev/xml_revisions.py
wikiteam3/dumpgenerator/dump/page/xmlrev/xml_revisions_page.py
wikiteam3/dumpgenerator/dump/redirect/allredirects.py
wikiteam3/dumpgenerator/dump/redirect/redirects_dump.py
wikiteam3/dumpgenerator/dump/xmldump/__init__.py
wikiteam3/dumpgenerator/dump/xmldump/xml_dump.py
wikiteam3/dumpgenerator/dump/xmldump/xml_header.py
wikiteam3/dumpgenerator/dump/xmldump/xml_integrity.py
wikiteam3/dumpgenerator/dump/xmldump/xml_truncate.py
wikiteam3/dumpgenerator/exceptions.py
wikiteam3/dumpgenerator/log/__init__.py
wikiteam3_fork_proxy-1.0.0.dist-info/METADATA
wikiteam3_fork_proxy-1.0.0.dist-info/WHEEL
wikiteam3_fork_proxy-1.0.0.dist-info/entry_points.txt
wikiteam3_fork_proxy-1.0.0.dist-info/licenses/LICENSE
wikiteam3_fork_proxy-1.0.0.dist-info/RECORD
