Metadata-Version: 2.1
Name: wikiteam3-fork-proxy
Version: 1.0.0
Summary: Tools for downloading and preserving MediaWikis. We archive MediaWikis, from Wikipedia to tiniest wikis.
Keywords: archiveteam,mediawiki,wikiteam,wikiteam3,preservation,wiki,wikipedia
Author: emijrp, nemobis, randomnetcat, NyaMisty, PiRSquared17, Hydriz, mramin22
Author-Email: yzqzss <yzqzss@saveweb.org>
Maintainer-Email: yzqzss <yzqzss@saveweb.org>, mramin22 <dadgaramin96@gmail.com>
License: GPL-3.0-or-later
Classifier: Environment :: Console
Classifier: Intended Audience :: Education
Classifier: Intended Audience :: End Users/Desktop
Classifier: Intended Audience :: Information Technology
Classifier: Intended Audience :: Legal Industry
Classifier: Intended Audience :: Science/Research
Classifier: Intended Audience :: System Administrators
Classifier: Natural Language :: English
Classifier: Operating System :: OS Independent
Classifier: Topic :: Communications
Classifier: Topic :: Internet
Classifier: Topic :: Internet :: WWW/HTTP :: Dynamic Content :: Wiki
Classifier: Topic :: Scientific/Engineering :: Information Analysis
Classifier: Topic :: Sociology :: History
Classifier: Topic :: System :: Archiving
Classifier: Topic :: System :: Archiving :: Backup
Classifier: Topic :: Utilities
Project-URL: repository, https://github.com/TogetherCrew/wikiteam3
Requires-Python: <4.0.0,>=3.8.1
Requires-Dist: requests<3.0.0,>=2.32.3
Requires-Dist: internetarchive<5.0.0,>=4.1.0
Requires-Dist: lxml<6.0.0,>=5.2.2
Requires-Dist: mwclient<1.0.0,>=0.10.1
Requires-Dist: file-read-backwards<4.0.0,>=3.1.0
Requires-Dist: python-slugify<9.0.0,>=8.0.4
